derivermodule/__init__.py
derivermodule/const.py
derivermodule/files.py
derivermodule/imagestack.py
derivermodule/logger.py
derivermodule/metadata.py
derivermodule/scandata.py
derivermodule/task.py
derivermodule/version.py
internetarchive_deriver_module-1.0.2.dist-info/AUTHORS
internetarchive_deriver_module-1.0.2.dist-info/COPYING
internetarchive_deriver_module-1.0.2.dist-info/LICENSE.TXT
internetarchive_deriver_module-1.0.2.dist-info/METADATA
internetarchive_deriver_module-1.0.2.dist-info/WHEEL
internetarchive_deriver_module-1.0.2.dist-info/top_level.txt
internetarchive_deriver_module-1.0.2.dist-info/RECORD
