Metadata-Version: 2.1
Name: internetarchive-deriver-module
Version: 1.0.2
Summary: Python derivermodule package
Home-page: https://git.archive.org/merlijn/python-derivermodule
Author: Merlijn Boris Wolf Wajer
Author-email: merlijn@archive.org
License: AGPL-3.0
Download-URL: https://git.archive.org/merlijn/python-derivermodule/-/archive/1.0.0/python-derivermodule-1.0.2.tar.gz
Keywords: Deriver,Internet Archive
Platform: UNKNOWN
Classifier: Development Status :: 3 - Alpha
Classifier: Intended Audience :: Developers
Classifier: License :: OSI Approved :: GNU Affero General Public License v3
Classifier: Programming Language :: Python :: 3
Requires-Python: >=3.6
License-File: LICENSE.TXT
License-File: COPYING
License-File: AUTHORS
Requires-Dist: xmltodict (==0.12.0)
